{
  "id" : 309,
  "handle" : "aimer",
  "countHistoryTasks" : 3,
  "historyTasks" : [ {
    "id" : 30002667,
    "name" : "Market Visualization",
    "type" : "DEVELOP",
    "subType" : "DEVELOPMENT",
    "technologies" : [ "Java Application", "HTML", "JavaScript", "AJAX" ],
    "status" : "Completed",
    "postingDate" : "2007-11-15",
    "registrationEndDate" : "2007-11-18",
    "submissionEndDate" : "2007-11-22",
    "prizes" : [ 800.0, 400.0 ],
    "numRegistrants" : 9,
    "registrants" : [ {
      "handle" : "Cagi",
      "registrationDate" : "2007-11-15"
    }, {
      "handle" : "onsky",
      "registrationDate" : "2007-11-15"
    }, {
      "handle" : "xueshantujiu",
      "registrationDate" : "2007-11-15"
    }, {
      "handle" : "dybowskjr",
      "registrationDate" : "2007-11-16"
    }, {
      "handle" : "securityman",
      "registrationDate" : "2007-11-16"
    }, {
      "handle" : "tyrian",
      "registrationDate" : "2007-11-16"
    }, {
      "handle" : "aimer",
      "registrationDate" : "2007-11-16"
    }, {
      "handle" : "ttmydung",
      "registrationDate" : "2007-11-18"
    }, {
      "handle" : "KLW",
      "registrationDate" : "2007-11-18"
    } ],
    "numSubmitters" : 3,
    "submitters" : [ {
      "handle" : "aimer",
      "placement" : 1,
      "score" : 96.63,
      "submissionDate" : "2007-11-22"
    }, {
      "handle" : "KLW",
      "placement" : 2,
      "score" : 82.36,
      "submissionDate" : "2007-11-22"
    }, {
      "handle" : "onsky",
      "placement" : -1,
      "score" : 0.0,
      "submissionDate" : "2007-11-22"
    } ]
  }, {
    "id" : 30002683,
    "name" : "Markets Performers",
    "type" : "DEVELOP",
    "subType" : "DEVELOPMENT",
    "technologies" : [ "Java", "JavaBean", "Java Application", "Web Services", "XML", "HTTP", "Spring", "Castor" ],
    "status" : "Completed",
    "postingDate" : "2007-11-01",
    "registrationEndDate" : "2007-11-04",
    "submissionEndDate" : "2007-11-09",
    "prizes" : [ 500.0, 250.0 ],
    "numRegistrants" : 16,
    "registrants" : [ {
      "handle" : "ylouis",
      "registrationDate" : "2007-11-04"
    }, {
      "handle" : "s80-20",
      "registrationDate" : "2007-11-01"
    }, {
      "handle" : "keyer",
      "registrationDate" : "2007-11-02"
    }, {
      "handle" : "kr00tki",
      "registrationDate" : "2007-11-02"
    }, {
      "handle" : "ttmydung",
      "registrationDate" : "2007-11-02"
    }, {
      "handle" : "ljsheng",
      "registrationDate" : "2007-11-03"
    }, {
      "handle" : "wang1234",
      "registrationDate" : "2007-11-03"
    }, {
      "handle" : "aoaoer88",
      "registrationDate" : "2007-11-03"
    }, {
      "handle" : "odiboni",
      "registrationDate" : "2007-11-03"
    }, {
      "handle" : "j2ee.solutions",
      "registrationDate" : "2007-11-03"
    }, {
      "handle" : "fionazoe",
      "registrationDate" : "2007-11-03"
    }, {
      "handle" : "omalinin",
      "registrationDate" : "2007-11-04"
    }, {
      "handle" : "aimer",
      "registrationDate" : "2007-11-04"
    }, {
      "handle" : "moon.river",
      "registrationDate" : "2007-11-04"
    }, {
      "handle" : "liangby",
      "registrationDate" : "2007-11-04"
    }, {
      "handle" : "soa_master",
      "registrationDate" : "2007-11-01"
    } ],
    "numSubmitters" : 2,
    "submitters" : [ {
      "handle" : "moon.river",
      "placement" : 1,
      "score" : 85.32,
      "submissionDate" : "2007-11-08"
    }, {
      "handle" : "ylouis",
      "placement" : 2,
      "score" : 80.14,
      "submissionDate" : "2007-11-09"
    } ]
  }, {
    "id" : 30002806,
    "name" : "Layout Engine",
    "type" : "DEVELOP",
    "subType" : "DEVELOPMENT",
    "technologies" : [ "C#", ".NET 2.0" ],
    "status" : "Completed",
    "postingDate" : "2007-11-01",
    "registrationEndDate" : "2007-11-04",
    "submissionEndDate" : "2007-11-08",
    "prizes" : [ 500.0, 250.0 ],
    "numRegistrants" : 11,
    "registrants" : [ {
      "handle" : "cs_guang",
      "registrationDate" : "2007-11-01"
    }, {
      "handle" : "goldlevi",
      "registrationDate" : "2007-11-01"
    }, {
      "handle" : "miceddie",
      "registrationDate" : "2007-11-01"
    }, {
      "handle" : "GMania",
      "registrationDate" : "2007-11-02"
    }, {
      "handle" : "gangli_tj07",
      "registrationDate" : "2007-11-02"
    }, {
      "handle" : "nanchen",
      "registrationDate" : "2007-11-02"
    }, {
      "handle" : "akinwale",
      "registrationDate" : "2007-11-02"
    }, {
      "handle" : "lifangluo",
      "registrationDate" : "2007-11-02"
    }, {
      "handle" : "kurtrips",
      "registrationDate" : "2007-11-03"
    }, {
      "handle" : "rainday",
      "registrationDate" : "2007-11-04"
    }, {
      "handle" : "aimer",
      "registrationDate" : "2007-11-04"
    } ],
    "numSubmitters" : 2,
    "submitters" : [ {
      "handle" : "kurtrips",
      "placement" : 1,
      "score" : 80.38,
      "submissionDate" : "2007-11-07"
    }, {
      "handle" : "akinwale",
      "placement" : 2,
      "score" : 63.73,
      "submissionDate" : "2007-11-07"
    } ]
  } ]
}