{
  "id" : 8562,
  "handle" : "DaraK",
  "countHistoryTasks" : 177,
  "historyTasks" : null,
  "taskResult" : [ {
    "id" : 30108611,
    "postingDate" : "2019-11-30",
    "registrationDate" : "2019-11-30",
    "submissionDate" : null,
    "placement" : -1,
    "score" : 0.0
  }, {
    "id" : 30108612,
    "postingDate" : "2019-11-30",
    "registrationDate" : "2019-11-30",
    "submissionDate" : null,
    "placement" : -1,
    "score" : 0.0
  }, {
    "id" : 30108491,
    "postingDate" : "2019-11-29",
    "registrationDate" : "2019-11-29",
    "submissionDate" : null,
    "placement" : -1,
    "score" : 0.0
  }, {
    "id" : 30103841,
    "postingDate" : "2019-11-27",
    "registrationDate" : "2019-11-27",
    "submissionDate" : null,
    "placement" : -1,
    "score" : 0.0
  }, {
    "id" : 30105171,
    "postingDate" : "2019-11-22",
    "registrationDate" : "2019-11-22",
    "submissionDate" : null,
    "placement" : -1,
    "score" : 0.0
  }, {
    "id" : 30107267,
    "postingDate" : "2019-11-19",
    "registrationDate" : "2019-11-19",
    "submissionDate" : null,
    "placement" : -1,
    "score" : 0.0
  }, {
    "id" : 30106916,
    "postingDate" : "2019-11-16",
    "registrationDate" : "2019-11-16",
    "submissionDate" : null,
    "placement" : -1,
    "score" : 0.0
  }, {
    "id" : 30104182,
    "postingDate" : "2019-10-18",
    "registrationDate" : "2019-10-18",
    "submissionDate" : null,
    "placement" : -1,
    "score" : 0.0
  }, {
    "id" : 30106897,
    "postingDate" : "2019-11-15",
    "registrationDate" : "2019-11-15",
    "submissionDate" : null,
    "placement" : -1,
    "score" : 0.0
  }, {
    "id" : 30106762,
    "postingDate" : "2019-11-14",
    "registrationDate" : "2019-11-14",
    "submissionDate" : null,
    "placement" : -1,
    "score" : 0.0
  }, {
    "id" : 30106770,
    "postingDate" : "2019-11-14",
    "registrationDate" : "2019-11-14",
    "submissionDate" : null,
    "placement" : -1,
    "score" : 0.0
  }, {
    "id" : 30105831,
    "postingDate" : "2019-11-06",
    "registrationDate" : "2019-11-06",
    "submissionDate" : null,
    "placement" : -1,
    "score" : 0.0
  }, {
    "id" : 30105733,
    "postingDate" : "2019-11-04",
    "registrationDate" : "2019-11-04",
    "submissionDate" : null,
    "placement" : -1,
    "score" : 0.0
  }, {
    "id" : 30105169,
    "postingDate" : "2019-10-26",
    "registrationDate" : "2019-10-26",
    "submissionDate" : null,
    "placement" : -1,
    "score" : 0.0
  }, {
    "id" : 30105092,
    "postingDate" : "2019-10-25",
    "registrationDate" : "2019-10-25",
    "submissionDate" : null,
    "placement" : -1,
    "score" : 0.0
  }, {
    "id" : 30104447,
    "postingDate" : "2019-10-22",
    "registrationDate" : "2019-10-22",
    "submissionDate" : null,
    "placement" : -1,
    "score" : 0.0
  }, {
    "id" : 30104249,
    "postingDate" : "2019-10-14",
    "registrationDate" : "2019-10-14",
    "submissionDate" : null,
    "placement" : -1,
    "score" : 0.0
  }, {
    "id" : 30103942,
    "postingDate" : "2019-10-07",
    "registrationDate" : "2019-10-07",
    "submissionDate" : null,
    "placement" : -1,
    "score" : 0.0
  }, {
    "id" : 30104405,
    "postingDate" : "2019-10-15",
    "registrationDate" : "2019-10-15",
    "submissionDate" : null,
    "placement" : -1,
    "score" : 0.0
  }, {
    "id" : 30104625,
    "postingDate" : "2019-10-19",
    "registrationDate" : "2019-10-19",
    "submissionDate" : null,
    "placement" : -1,
    "score" : 0.0
  }, {
    "id" : 30103958,
    "postingDate" : "2019-10-07",
    "registrationDate" : "2019-10-07",
    "submissionDate" : null,
    "placement" : -1,
    "score" : 0.0
  }, {
    "id" : 30104376,
    "postingDate" : "2019-10-15",
    "registrationDate" : "2019-10-15",
    "submissionDate" : null,
    "placement" : -1,
    "score" : 0.0
  }, {
    "id" : 30103753,
    "postingDate" : "2019-10-01",
    "registrationDate" : "2019-10-01",
    "submissionDate" : null,
    "placement" : -1,
    "score" : 0.0
  }, {
    "id" : 30099184,
    "postingDate" : "2019-08-14",
    "registrationDate" : "2019-08-14",
    "submissionDate" : null,
    "placement" : -1,
    "score" : 0.0
  }, {
    "id" : 30103892,
    "postingDate" : "2019-10-04",
    "registrationDate" : "2019-10-04",
    "submissionDate" : null,
    "placement" : -1,
    "score" : 0.0
  }, {
    "id" : 30103914,
    "postingDate" : "2019-10-05",
    "registrationDate" : "2019-10-05",
    "submissionDate" : null,
    "placement" : -1,
    "score" : 0.0
  }, {
    "id" : 30101622,
    "postingDate" : "2019-10-04",
    "registrationDate" : "2019-10-04",
    "submissionDate" : null,
    "placement" : -1,
    "score" : 0.0
  }, {
    "id" : 30103191,
    "postingDate" : "2019-09-24",
    "registrationDate" : "2019-09-24",
    "submissionDate" : null,
    "placement" : -1,
    "score" : 0.0
  }, {
    "id" : 30095463,
    "postingDate" : "2019-10-01",
    "registrationDate" : "2019-10-01",
    "submissionDate" : null,
    "placement" : -1,
    "score" : 0.0
  }, {
    "id" : 30103195,
    "postingDate" : "2019-09-26",
    "registrationDate" : "2019-09-26",
    "submissionDate" : null,
    "placement" : -1,
    "score" : 0.0
  }, {
    "id" : 30103590,
    "postingDate" : "2019-09-29",
    "registrationDate" : "2019-09-29",
    "submissionDate" : null,
    "placement" : -1,
    "score" : 0.0
  }, {
    "id" : 30103087,
    "postingDate" : "2019-09-21",
    "registrationDate" : "2019-09-21",
    "submissionDate" : null,
    "placement" : -1,
    "score" : 0.0
  }, {
    "id" : 30103394,
    "postingDate" : "2019-09-26",
    "registrationDate" : "2019-09-26",
    "submissionDate" : null,
    "placement" : -1,
    "score" : 0.0
  }, {
    "id" : 30103090,
    "postingDate" : "2019-09-22",
    "registrationDate" : "2019-09-22",
    "submissionDate" : null,
    "placement" : -1,
    "score" : 0.0
  }, {
    "id" : 30103145,
    "postingDate" : "2019-09-23",
    "registrationDate" : "2019-09-23",
    "submissionDate" : null,
    "placement" : -1,
    "score" : 0.0
  }, {
    "id" : 30103177,
    "postingDate" : "2019-09-24",
    "registrationDate" : "2019-09-24",
    "submissionDate" : null,
    "placement" : -1,
    "score" : 0.0
  }, {
    "id" : 30102263,
    "postingDate" : "2019-09-12",
    "registrationDate" : "2019-09-12",
    "submissionDate" : null,
    "placement" : -1,
    "score" : 0.0
  }, {
    "id" : 30103009,
    "postingDate" : "2019-09-20",
    "registrationDate" : "2019-09-20",
    "submissionDate" : null,
    "placement" : -1,
    "score" : 0.0
  }, {
    "id" : 30102897,
    "postingDate" : "2019-09-18",
    "registrationDate" : "2019-09-18",
    "submissionDate" : null,
    "placement" : -1,
    "score" : 0.0
  }, {
    "id" : 30102274,
    "postingDate" : "2019-09-13",
    "registrationDate" : "2019-09-14",
    "submissionDate" : null,
    "placement" : -1,
    "score" : 0.0
  }, {
    "id" : 30102127,
    "postingDate" : "2019-09-12",
    "registrationDate" : "2019-09-12",
    "submissionDate" : null,
    "placement" : -1,
    "score" : 0.0
  }, {
    "id" : 30090464,
    "postingDate" : "2019-09-17",
    "registrationDate" : "2019-09-17",
    "submissionDate" : null,
    "placement" : -1,
    "score" : 0.0
  }, {
    "id" : 30090463,
    "postingDate" : "2019-09-17",
    "registrationDate" : "2019-09-17",
    "submissionDate" : null,
    "placement" : -1,
    "score" : 0.0
  }, {
    "id" : 30102275,
    "postingDate" : "2019-09-15",
    "registrationDate" : "2019-09-15",
    "submissionDate" : null,
    "placement" : -1,
    "score" : 0.0
  }, {
    "id" : 30103088,
    "postingDate" : "2019-09-21",
    "registrationDate" : "2019-09-21",
    "submissionDate" : null,
    "placement" : -1,
    "score" : 0.0
  }, {
    "id" : 30103089,
    "postingDate" : "2019-09-21",
    "registrationDate" : "2019-09-21",
    "submissionDate" : null,
    "placement" : -1,
    "score" : 0.0
  }, {
    "id" : 30101502,
    "postingDate" : "2019-09-06",
    "registrationDate" : "2019-09-06",
    "submissionDate" : null,
    "placement" : -1,
    "score" : 0.0
  }, {
    "id" : 30101930,
    "postingDate" : "2019-09-12",
    "registrationDate" : "2019-09-12",
    "submissionDate" : null,
    "placement" : -1,
    "score" : 0.0
  }, {
    "id" : 30102717,
    "postingDate" : "2019-09-17",
    "registrationDate" : "2019-09-17",
    "submissionDate" : null,
    "placement" : -1,
    "score" : 0.0
  }, {
    "id" : 30102678,
    "postingDate" : "2019-09-16",
    "registrationDate" : "2019-09-16",
    "submissionDate" : null,
    "placement" : -1,
    "score" : 0.0
  }, {
    "id" : 30102567,
    "postingDate" : "2019-09-16",
    "registrationDate" : "2019-09-16",
    "submissionDate" : null,
    "placement" : -1,
    "score" : 0.0
  }, {
    "id" : 30101630,
    "postingDate" : "2019-09-08",
    "registrationDate" : "2019-09-08",
    "submissionDate" : null,
    "placement" : -1,
    "score" : 0.0
  }, {
    "id" : 30101629,
    "postingDate" : "2019-09-08",
    "registrationDate" : "2019-09-08",
    "submissionDate" : null,
    "placement" : -1,
    "score" : 0.0
  }, {
    "id" : 30102680,
    "postingDate" : "2019-09-16",
    "registrationDate" : "2019-09-16",
    "submissionDate" : null,
    "placement" : -1,
    "score" : 0.0
  }, {
    "id" : 30102683,
    "postingDate" : "2019-09-16",
    "registrationDate" : "2019-09-16",
    "submissionDate" : null,
    "placement" : -1,
    "score" : 0.0
  }, {
    "id" : 30102676,
    "postingDate" : "2019-09-16",
    "registrationDate" : "2019-09-16",
    "submissionDate" : null,
    "placement" : -1,
    "score" : 0.0
  }, {
    "id" : 30102069,
    "postingDate" : "2019-09-11",
    "registrationDate" : "2019-09-11",
    "submissionDate" : null,
    "placement" : -1,
    "score" : 0.0
  }, {
    "id" : 30102518,
    "postingDate" : "2019-09-16",
    "registrationDate" : "2019-09-16",
    "submissionDate" : null,
    "placement" : -1,
    "score" : 0.0
  }, {
    "id" : 30101700,
    "postingDate" : "2019-09-09",
    "registrationDate" : "2019-09-09",
    "submissionDate" : null,
    "placement" : -1,
    "score" : 0.0
  }, {
    "id" : 30102495,
    "postingDate" : "2019-09-16",
    "registrationDate" : "2019-09-16",
    "submissionDate" : null,
    "placement" : -1,
    "score" : 0.0
  }, {
    "id" : 30102491,
    "postingDate" : "2019-09-16",
    "registrationDate" : "2019-09-16",
    "submissionDate" : null,
    "placement" : -1,
    "score" : 0.0
  }, {
    "id" : 30102442,
    "postingDate" : "2019-09-16",
    "registrationDate" : "2019-09-16",
    "submissionDate" : null,
    "placement" : -1,
    "score" : 0.0
  }, {
    "id" : 30102443,
    "postingDate" : "2019-09-16",
    "registrationDate" : "2019-09-16",
    "submissionDate" : null,
    "placement" : -1,
    "score" : 0.0
  }, {
    "id" : 30102441,
    "postingDate" : "2019-09-15",
    "registrationDate" : "2019-09-15",
    "submissionDate" : null,
    "placement" : -1,
    "score" : 0.0
  }, {
    "id" : 30102438,
    "postingDate" : "2019-09-15",
    "registrationDate" : "2019-09-15",
    "submissionDate" : null,
    "placement" : -1,
    "score" : 0.0
  }, {
    "id" : 30102382,
    "postingDate" : "2019-09-13",
    "registrationDate" : "2019-09-13",
    "submissionDate" : null,
    "placement" : -1,
    "score" : 0.0
  }, {
    "id" : 30101628,
    "postingDate" : "2019-09-07",
    "registrationDate" : "2019-09-07",
    "submissionDate" : null,
    "placement" : -1,
    "score" : 0.0
  }, {
    "id" : 30101689,
    "postingDate" : "2019-09-08",
    "registrationDate" : "2019-09-08",
    "submissionDate" : null,
    "placement" : -1,
    "score" : 0.0
  }, {
    "id" : 30101290,
    "postingDate" : "2019-09-04",
    "registrationDate" : "2019-09-04",
    "submissionDate" : null,
    "placement" : -1,
    "score" : 0.0
  }, {
    "id" : 30100621,
    "postingDate" : "2019-08-29",
    "registrationDate" : "2019-08-29",
    "submissionDate" : null,
    "placement" : -1,
    "score" : 0.0
  }, {
    "id" : 30100514,
    "postingDate" : "2019-08-28",
    "registrationDate" : "2019-08-28",
    "submissionDate" : null,
    "placement" : -1,
    "score" : 0.0
  }, {
    "id" : 30100120,
    "postingDate" : "2019-08-22",
    "registrationDate" : "2019-08-22",
    "submissionDate" : null,
    "placement" : -1,
    "score" : 0.0
  }, {
    "id" : 30100149,
    "postingDate" : "2019-08-25",
    "registrationDate" : "2019-08-25",
    "submissionDate" : null,
    "placement" : -1,
    "score" : 0.0
  }, {
    "id" : 30100349,
    "postingDate" : "2019-08-26",
    "registrationDate" : "2019-08-26",
    "submissionDate" : null,
    "placement" : -1,
    "score" : 0.0
  }, {
    "id" : 30099291,
    "postingDate" : "2019-08-15",
    "registrationDate" : "2019-08-15",
    "submissionDate" : null,
    "placement" : -1,
    "score" : 0.0
  }, {
    "id" : 30100119,
    "postingDate" : "2019-08-22",
    "registrationDate" : "2019-08-22",
    "submissionDate" : null,
    "placement" : -1,
    "score" : 0.0
  }, {
    "id" : 30100196,
    "postingDate" : "2019-08-24",
    "registrationDate" : "2019-08-24",
    "submissionDate" : null,
    "placement" : -1,
    "score" : 0.0
  }, {
    "id" : 30100163,
    "postingDate" : "2019-08-23",
    "registrationDate" : "2019-08-23",
    "submissionDate" : null,
    "placement" : -1,
    "score" : 0.0
  }, {
    "id" : 30095825,
    "postingDate" : "2019-07-19",
    "registrationDate" : "2019-07-19",
    "submissionDate" : null,
    "placement" : -1,
    "score" : 0.0
  }, {
    "id" : 30095824,
    "postingDate" : "2019-07-19",
    "registrationDate" : "2019-07-19",
    "submissionDate" : null,
    "placement" : -1,
    "score" : 0.0
  }, {
    "id" : 30095823,
    "postingDate" : "2019-07-19",
    "registrationDate" : "2019-07-19",
    "submissionDate" : null,
    "placement" : -1,
    "score" : 0.0
  }, {
    "id" : 30095821,
    "postingDate" : "2019-07-19",
    "registrationDate" : "2019-07-19",
    "submissionDate" : null,
    "placement" : -1,
    "score" : 0.0
  }, {
    "id" : 30099581,
    "postingDate" : "2019-08-18",
    "registrationDate" : "2019-08-18",
    "submissionDate" : null,
    "placement" : -1,
    "score" : 0.0
  }, {
    "id" : 30099190,
    "postingDate" : "2019-08-14",
    "registrationDate" : "2019-08-14",
    "submissionDate" : null,
    "placement" : -1,
    "score" : 0.0
  }, {
    "id" : 30099187,
    "postingDate" : "2019-08-15",
    "registrationDate" : "2019-08-15",
    "submissionDate" : null,
    "placement" : -1,
    "score" : 0.0
  }, {
    "id" : 30099126,
    "postingDate" : "2019-08-12",
    "registrationDate" : "2019-08-12",
    "submissionDate" : null,
    "placement" : -1,
    "score" : 0.0
  }, {
    "id" : 30099125,
    "postingDate" : "2019-08-12",
    "registrationDate" : "2019-08-12",
    "submissionDate" : null,
    "placement" : -1,
    "score" : 0.0
  }, {
    "id" : 30098701,
    "postingDate" : "2019-08-07",
    "registrationDate" : "2019-08-07",
    "submissionDate" : "2019-08-07",
    "placement" : -1,
    "score" : 0.0
  }, {
    "id" : 30098863,
    "postingDate" : "2019-08-09",
    "registrationDate" : "2019-08-09",
    "submissionDate" : null,
    "placement" : -1,
    "score" : 0.0
  }, {
    "id" : 30098430,
    "postingDate" : "2019-08-08",
    "registrationDate" : "2019-08-08",
    "submissionDate" : null,
    "placement" : -1,
    "score" : 0.0
  }, {
    "id" : 30097294,
    "postingDate" : "2019-07-25",
    "registrationDate" : "2019-07-25",
    "submissionDate" : null,
    "placement" : -1,
    "score" : 0.0
  }, {
    "id" : 30097979,
    "postingDate" : "2019-07-29",
    "registrationDate" : "2019-07-29",
    "submissionDate" : null,
    "placement" : -1,
    "score" : 0.0
  }, {
    "id" : 30098510,
    "postingDate" : "2019-08-06",
    "registrationDate" : "2019-08-06",
    "submissionDate" : null,
    "placement" : -1,
    "score" : 0.0
  }, {
    "id" : 30092166,
    "postingDate" : "2019-05-31",
    "registrationDate" : "2019-05-31",
    "submissionDate" : null,
    "placement" : -1,
    "score" : 0.0
  }, {
    "id" : 30096681,
    "postingDate" : "2019-07-24",
    "registrationDate" : "2019-07-24",
    "submissionDate" : null,
    "placement" : -1,
    "score" : 0.0
  }, {
    "id" : 30097331,
    "postingDate" : "2019-07-25",
    "registrationDate" : "2019-07-25",
    "submissionDate" : null,
    "placement" : -1,
    "score" : 0.0
  }, {
    "id" : 30097314,
    "postingDate" : "2019-07-25",
    "registrationDate" : "2019-07-25",
    "submissionDate" : null,
    "placement" : -1,
    "score" : 0.0
  }, {
    "id" : 30098248,
    "postingDate" : "2019-08-03",
    "registrationDate" : "2019-08-03",
    "submissionDate" : null,
    "placement" : -1,
    "score" : 0.0
  }, {
    "id" : 30098395,
    "postingDate" : "2019-08-03",
    "registrationDate" : "2019-08-03",
    "submissionDate" : null,
    "placement" : -1,
    "score" : 0.0
  }, {
    "id" : 30098394,
    "postingDate" : "2019-08-03",
    "registrationDate" : "2019-08-03",
    "submissionDate" : null,
    "placement" : -1,
    "score" : 0.0
  }, {
    "id" : 30096591,
    "postingDate" : "2019-07-23",
    "registrationDate" : "2019-07-23",
    "submissionDate" : null,
    "placement" : -1,
    "score" : 0.0
  }, {
    "id" : 30097813,
    "postingDate" : "2019-07-27",
    "registrationDate" : "2019-07-27",
    "submissionDate" : null,
    "placement" : -1,
    "score" : 0.0
  }, {
    "id" : 30095791,
    "postingDate" : "2019-07-22",
    "registrationDate" : "2019-07-22",
    "submissionDate" : null,
    "placement" : -1,
    "score" : 0.0
  }, {
    "id" : 30096704,
    "postingDate" : "2019-07-24",
    "registrationDate" : "2019-07-24",
    "submissionDate" : null,
    "placement" : -1,
    "score" : 0.0
  }, {
    "id" : 30095683,
    "postingDate" : "2019-07-16",
    "registrationDate" : "2019-07-16",
    "submissionDate" : null,
    "placement" : -1,
    "score" : 0.0
  }, {
    "id" : 30095840,
    "postingDate" : "2019-07-16",
    "registrationDate" : "2019-07-16",
    "submissionDate" : null,
    "placement" : -1,
    "score" : 0.0
  }, {
    "id" : 30095687,
    "postingDate" : "2019-07-13",
    "registrationDate" : "2019-07-13",
    "submissionDate" : null,
    "placement" : -1,
    "score" : 0.0
  }, {
    "id" : 30095496,
    "postingDate" : "2019-07-11",
    "registrationDate" : "2019-07-15",
    "submissionDate" : null,
    "placement" : -1,
    "score" : 0.0
  }, {
    "id" : 30095596,
    "postingDate" : "2019-07-11",
    "registrationDate" : "2019-07-11",
    "submissionDate" : null,
    "placement" : -1,
    "score" : 0.0
  }, {
    "id" : 30095732,
    "postingDate" : "2019-07-16",
    "registrationDate" : "2019-07-16",
    "submissionDate" : null,
    "placement" : -1,
    "score" : 0.0
  }, {
    "id" : 30096412,
    "postingDate" : "2019-07-20",
    "registrationDate" : "2019-07-20",
    "submissionDate" : null,
    "placement" : -1,
    "score" : 0.0
  }, {
    "id" : 30095550,
    "postingDate" : "2019-07-11",
    "registrationDate" : "2019-07-11",
    "submissionDate" : null,
    "placement" : -1,
    "score" : 0.0
  }, {
    "id" : 30095549,
    "postingDate" : "2019-07-11",
    "registrationDate" : "2019-07-11",
    "submissionDate" : null,
    "placement" : -1,
    "score" : 0.0
  }, {
    "id" : 30096336,
    "postingDate" : "2019-07-20",
    "registrationDate" : "2019-07-20",
    "submissionDate" : null,
    "placement" : -1,
    "score" : 0.0
  }, {
    "id" : 30095466,
    "postingDate" : "2019-07-10",
    "registrationDate" : "2019-07-10",
    "submissionDate" : null,
    "placement" : -1,
    "score" : 0.0
  }, {
    "id" : 30095862,
    "postingDate" : "2019-07-17",
    "registrationDate" : "2019-07-17",
    "submissionDate" : null,
    "placement" : -1,
    "score" : 0.0
  }, {
    "id" : 30095860,
    "postingDate" : "2019-07-17",
    "registrationDate" : "2019-07-17",
    "submissionDate" : null,
    "placement" : -1,
    "score" : 0.0
  }, {
    "id" : 30090467,
    "postingDate" : "2019-07-12",
    "registrationDate" : "2019-07-12",
    "submissionDate" : null,
    "placement" : -1,
    "score" : 0.0
  }, {
    "id" : 30095932,
    "postingDate" : "2019-07-17",
    "registrationDate" : "2019-07-17",
    "submissionDate" : null,
    "placement" : -1,
    "score" : 0.0
  }, {
    "id" : 30095657,
    "postingDate" : "2019-07-12",
    "registrationDate" : "2019-07-12",
    "submissionDate" : null,
    "placement" : -1,
    "score" : 0.0
  }, {
    "id" : 30095272,
    "postingDate" : "2019-07-07",
    "registrationDate" : "2019-07-07",
    "submissionDate" : null,
    "placement" : -1,
    "score" : 0.0
  }, {
    "id" : 30095699,
    "postingDate" : "2019-07-14",
    "registrationDate" : "2019-07-14",
    "submissionDate" : null,
    "placement" : -1,
    "score" : 0.0
  }, {
    "id" : 30095561,
    "postingDate" : "2019-07-11",
    "registrationDate" : "2019-07-11",
    "submissionDate" : null,
    "placement" : -1,
    "score" : 0.0
  }, {
    "id" : 30095470,
    "postingDate" : "2019-07-10",
    "registrationDate" : "2019-07-10",
    "submissionDate" : null,
    "placement" : -1,
    "score" : 0.0
  }, {
    "id" : 30094478,
    "postingDate" : "2019-06-27",
    "registrationDate" : "2019-06-27",
    "submissionDate" : null,
    "placement" : -1,
    "score" : 0.0
  }, {
    "id" : 30094664,
    "postingDate" : "2019-07-01",
    "registrationDate" : "2019-07-01",
    "submissionDate" : null,
    "placement" : -1,
    "score" : 0.0
  }, {
    "id" : 30094663,
    "postingDate" : "2019-07-01",
    "registrationDate" : "2019-07-01",
    "submissionDate" : null,
    "placement" : -1,
    "score" : 0.0
  }, {
    "id" : 30094583,
    "postingDate" : "2019-06-28",
    "registrationDate" : "2019-06-28",
    "submissionDate" : null,
    "placement" : -1,
    "score" : 0.0
  }, {
    "id" : 30094666,
    "postingDate" : "2019-07-01",
    "registrationDate" : "2019-07-01",
    "submissionDate" : null,
    "placement" : -1,
    "score" : 0.0
  }, {
    "id" : 30094611,
    "postingDate" : "2019-06-29",
    "registrationDate" : "2019-06-29",
    "submissionDate" : null,
    "placement" : -1,
    "score" : 0.0
  }, {
    "id" : 30094231,
    "postingDate" : "2019-06-25",
    "registrationDate" : "2019-06-25",
    "submissionDate" : null,
    "placement" : -1,
    "score" : 0.0
  }, {
    "id" : 30094310,
    "postingDate" : "2019-06-25",
    "registrationDate" : "2019-06-25",
    "submissionDate" : null,
    "placement" : -1,
    "score" : 0.0
  }, {
    "id" : 30093860,
    "postingDate" : "2019-06-20",
    "registrationDate" : "2019-06-20",
    "submissionDate" : null,
    "placement" : -1,
    "score" : 0.0
  }, {
    "id" : 30093331,
    "postingDate" : "2019-06-12",
    "registrationDate" : "2019-06-12",
    "submissionDate" : null,
    "placement" : -1,
    "score" : 0.0
  }, {
    "id" : 30091712,
    "postingDate" : "2019-05-27",
    "registrationDate" : "2019-05-27",
    "submissionDate" : null,
    "placement" : -1,
    "score" : 0.0
  }, {
    "id" : 30093581,
    "postingDate" : "2019-06-14",
    "registrationDate" : "2019-06-23",
    "submissionDate" : null,
    "placement" : -1,
    "score" : 0.0
  }, {
    "id" : 30093563,
    "postingDate" : "2019-06-14",
    "registrationDate" : "2019-06-14",
    "submissionDate" : null,
    "placement" : -1,
    "score" : 0.0
  }, {
    "id" : 30092787,
    "postingDate" : "2019-06-07",
    "registrationDate" : "2019-06-07",
    "submissionDate" : null,
    "placement" : -1,
    "score" : 0.0
  }, {
    "id" : 30093648,
    "postingDate" : "2019-06-17",
    "registrationDate" : "2019-06-17",
    "submissionDate" : null,
    "placement" : -1,
    "score" : 0.0
  }, {
    "id" : 30093813,
    "postingDate" : "2019-06-18",
    "registrationDate" : "2019-06-18",
    "submissionDate" : null,
    "placement" : -1,
    "score" : 0.0
  }, {
    "id" : 30093279,
    "postingDate" : "2019-06-12",
    "registrationDate" : "2019-06-12",
    "submissionDate" : null,
    "placement" : -1,
    "score" : 0.0
  }, {
    "id" : 30090953,
    "postingDate" : "2019-06-11",
    "registrationDate" : "2019-06-11",
    "submissionDate" : null,
    "placement" : -1,
    "score" : 0.0
  }, {
    "id" : 30092483,
    "postingDate" : "2019-06-06",
    "registrationDate" : "2019-06-06",
    "submissionDate" : null,
    "placement" : -1,
    "score" : 0.0
  }, {
    "id" : 30093527,
    "postingDate" : "2019-06-14",
    "registrationDate" : "2019-06-14",
    "submissionDate" : null,
    "placement" : -1,
    "score" : 0.0
  }, {
    "id" : 30093565,
    "postingDate" : "2019-06-15",
    "registrationDate" : "2019-06-15",
    "submissionDate" : null,
    "placement" : -1,
    "score" : 0.0
  }, {
    "id" : 30091862,
    "postingDate" : "2019-05-28",
    "registrationDate" : "2019-05-30",
    "submissionDate" : null,
    "placement" : -1,
    "score" : 0.0
  }, {
    "id" : 30092190,
    "postingDate" : "2019-06-06",
    "registrationDate" : "2019-06-06",
    "submissionDate" : null,
    "placement" : -1,
    "score" : 0.0
  }, {
    "id" : 30092207,
    "postingDate" : "2019-05-31",
    "registrationDate" : "2019-05-31",
    "submissionDate" : null,
    "placement" : -1,
    "score" : 0.0
  }, {
    "id" : 30092649,
    "postingDate" : "2019-06-05",
    "registrationDate" : "2019-06-05",
    "submissionDate" : null,
    "placement" : -1,
    "score" : 0.0
  }, {
    "id" : 30091792,
    "postingDate" : "2019-06-01",
    "registrationDate" : "2019-06-01",
    "submissionDate" : null,
    "placement" : -1,
    "score" : 0.0
  }, {
    "id" : 30091662,
    "postingDate" : "2019-05-24",
    "registrationDate" : "2019-05-24",
    "submissionDate" : null,
    "placement" : -1,
    "score" : 0.0
  }, {
    "id" : 30091975,
    "postingDate" : "2019-05-29",
    "registrationDate" : "2019-05-29",
    "submissionDate" : null,
    "placement" : -1,
    "score" : 0.0
  }, {
    "id" : 30092033,
    "postingDate" : "2019-06-02",
    "registrationDate" : "2019-06-02",
    "submissionDate" : null,
    "placement" : -1,
    "score" : 0.0
  }, {
    "id" : 30092311,
    "postingDate" : "2019-06-02",
    "registrationDate" : "2019-06-02",
    "submissionDate" : null,
    "placement" : -1,
    "score" : 0.0
  }, {
    "id" : 30092310,
    "postingDate" : "2019-06-02",
    "registrationDate" : "2019-06-02",
    "submissionDate" : null,
    "placement" : -1,
    "score" : 0.0
  }, {
    "id" : 30092302,
    "postingDate" : "2019-06-02",
    "registrationDate" : "2019-06-02",
    "submissionDate" : null,
    "placement" : -1,
    "score" : 0.0
  }, {
    "id" : 30091530,
    "postingDate" : "2019-05-26",
    "registrationDate" : "2019-05-27",
    "submissionDate" : null,
    "placement" : -1,
    "score" : 0.0
  }, {
    "id" : 30091642,
    "postingDate" : "2019-05-24",
    "registrationDate" : "2019-05-24",
    "submissionDate" : null,
    "placement" : -1,
    "score" : 0.0
  }, {
    "id" : 30091238,
    "postingDate" : "2019-05-22",
    "registrationDate" : "2019-05-22",
    "submissionDate" : null,
    "placement" : -1,
    "score" : 0.0
  }, {
    "id" : 30091595,
    "postingDate" : "2019-05-23",
    "registrationDate" : "2019-05-23",
    "submissionDate" : null,
    "placement" : -1,
    "score" : 0.0
  }, {
    "id" : 30091518,
    "postingDate" : "2019-05-23",
    "registrationDate" : "2019-05-23",
    "submissionDate" : null,
    "placement" : -1,
    "score" : 0.0
  }, {
    "id" : 30091651,
    "postingDate" : "2019-05-24",
    "registrationDate" : "2019-05-24",
    "submissionDate" : null,
    "placement" : -1,
    "score" : 0.0
  }, {
    "id" : 30090194,
    "postingDate" : "2019-05-09",
    "registrationDate" : "2019-05-09",
    "submissionDate" : null,
    "placement" : -1,
    "score" : 0.0
  }, {
    "id" : 30091160,
    "postingDate" : "2019-05-20",
    "registrationDate" : "2019-05-20",
    "submissionDate" : null,
    "placement" : -1,
    "score" : 0.0
  }, {
    "id" : 30090894,
    "postingDate" : "2019-05-15",
    "registrationDate" : "2019-05-15",
    "submissionDate" : null,
    "placement" : -1,
    "score" : 0.0
  }, {
    "id" : 30090882,
    "postingDate" : "2019-05-15",
    "registrationDate" : "2019-05-15",
    "submissionDate" : null,
    "placement" : -1,
    "score" : 0.0
  }, {
    "id" : 30090505,
    "postingDate" : "2019-05-10",
    "registrationDate" : "2019-05-10",
    "submissionDate" : null,
    "placement" : -1,
    "score" : 0.0
  }, {
    "id" : 30091078,
    "postingDate" : "2019-05-18",
    "registrationDate" : "2019-05-18",
    "submissionDate" : null,
    "placement" : -1,
    "score" : 0.0
  }, {
    "id" : 30090537,
    "postingDate" : "2019-05-12",
    "registrationDate" : "2019-05-12",
    "submissionDate" : null,
    "placement" : -1,
    "score" : 0.0
  }, {
    "id" : 30090886,
    "postingDate" : "2019-05-15",
    "registrationDate" : "2019-05-15",
    "submissionDate" : null,
    "placement" : -1,
    "score" : 0.0
  }, {
    "id" : 30090883,
    "postingDate" : "2019-05-15",
    "registrationDate" : "2019-05-15",
    "submissionDate" : null,
    "placement" : -1,
    "score" : 0.0
  }, {
    "id" : 30090871,
    "postingDate" : "2019-05-15",
    "registrationDate" : "2019-05-15",
    "submissionDate" : null,
    "placement" : -1,
    "score" : 0.0
  }, {
    "id" : 30090591,
    "postingDate" : "2019-05-13",
    "registrationDate" : "2019-05-13",
    "submissionDate" : null,
    "placement" : -1,
    "score" : 0.0
  }, {
    "id" : 30090515,
    "postingDate" : "2019-05-13",
    "registrationDate" : "2019-05-13",
    "submissionDate" : null,
    "placement" : -1,
    "score" : 0.0
  }, {
    "id" : 30090056,
    "postingDate" : "2019-05-03",
    "registrationDate" : "2019-05-03",
    "submissionDate" : null,
    "placement" : -1,
    "score" : 0.0
  }, {
    "id" : 30090173,
    "postingDate" : "2019-05-06",
    "registrationDate" : "2019-05-06",
    "submissionDate" : null,
    "placement" : -1,
    "score" : 0.0
  }, {
    "id" : 30090220,
    "postingDate" : "2019-05-07",
    "registrationDate" : "2019-05-07",
    "submissionDate" : null,
    "placement" : -1,
    "score" : 0.0
  } ]
}