{
  "id" : 1097,
  "handle" : "thomasjpfan",
  "countHistoryTasks" : 104,
  "historyTasks" : [ {
    "id" : 30079791
  }, {
    "id" : 30067224
  }, {
    "id" : 30064483
  }, {
    "id" : 30063682
  }, {
    "id" : 30061883
  }, {
    "id" : 16937
  }, {
    "id" : 16950
  }, {
    "id" : 30057672
  }, {
    "id" : 30054206
  }, {
    "id" : 30054554
  }, {
    "id" : 30054393
  }, {
    "id" : 30052220
  }, {
    "id" : 30051786
  }, {
    "id" : 30051629
  }, {
    "id" : 30051775
  }, {
    "id" : 30050554
  }, {
    "id" : 30050881
  }, {
    "id" : 30051225
  }, {
    "id" : 30051219
  }, {
    "id" : 30050998
  }, {
    "id" : 30051207
  }, {
    "id" : 30051061
  }, {
    "id" : 16510
  }, {
    "id" : 30050253
  }, {
    "id" : 16525
  }, {
    "id" : 30050764
  }, {
    "id" : 30050472
  }, {
    "id" : 30049940
  }, {
    "id" : 30050435
  }, {
    "id" : 30050424
  }, {
    "id" : 30049150
  }, {
    "id" : 30049788
  }, {
    "id" : 30049751
  }, {
    "id" : 30048772
  }, {
    "id" : 30049665
  }, {
    "id" : 30049330
  }, {
    "id" : 30049526
  }, {
    "id" : 30048771
  }, {
    "id" : 30049255
  }, {
    "id" : 30049403
  }, {
    "id" : 30049352
  }, {
    "id" : 30049317
  }, {
    "id" : 30048929
  }, {
    "id" : 30049238
  }, {
    "id" : 30049237
  }, {
    "id" : 30048656
  }, {
    "id" : 30049225
  }, {
    "id" : 30048506
  }, {
    "id" : 30049184
  }, {
    "id" : 30049165
  }, {
    "id" : 30049167
  }, {
    "id" : 30049126
  }, {
    "id" : 30048444
  }, {
    "id" : 30048827
  }, {
    "id" : 30049018
  }, {
    "id" : 30049013
  }, {
    "id" : 30048702
  }, {
    "id" : 30048723
  }, {
    "id" : 30048886
  }, {
    "id" : 30047867
  }, {
    "id" : 16307
  }, {
    "id" : 30048416
  }, {
    "id" : 30047767
  }, {
    "id" : 30048480
  }, {
    "id" : 30047484
  }, {
    "id" : 30047723
  }, {
    "id" : 30048324
  }, {
    "id" : 30048020
  }, {
    "id" : 16209
  }, {
    "id" : 30047649
  }, {
    "id" : 30047506
  }, {
    "id" : 30047528
  }, {
    "id" : 30047570
  }, {
    "id" : 30047473
  }, {
    "id" : 30047375
  }, {
    "id" : 30047374
  }, {
    "id" : 30047358
  }, {
    "id" : 30047070
  }, {
    "id" : 30042218
  }, {
    "id" : 30047202
  }, {
    "id" : 30047158
  }, {
    "id" : 30047232
  }, {
    "id" : 30047233
  }, {
    "id" : 30046831
  }, {
    "id" : 30047030
  }, {
    "id" : 30046982
  }, {
    "id" : 30046420
  }, {
    "id" : 30046899
  }, {
    "id" : 30046945
  }, {
    "id" : 30046929
  }, {
    "id" : 30046823
  }, {
    "id" : 30046753
  }, {
    "id" : 30046647
  }, {
    "id" : 16168
  }, {
    "id" : 30046731
  }, {
    "id" : 30046149
  }, {
    "id" : 30046376
  }, {
    "id" : 30046341
  }, {
    "id" : 30045514
  }, {
    "id" : 30042128
  }, {
    "id" : 30035530
  }, {
    "id" : 30045504
  }, {
    "id" : 30045372
  }, {
    "id" : 30045359
  } ]
}