{
  "id" : 4925,
  "handle" : "Fozz",
  "countHistoryTasks" : 30,
  "historyTasks" : [ {
    "id" : 14672
  }, {
    "id" : 14209
  }, {
    "id" : 13570
  }, {
    "id" : 30002651
  }, {
    "id" : 30002569
  }, {
    "id" : 30002525
  }, {
    "id" : 10862
  }, {
    "id" : 30002454
  }, {
    "id" : 30002358
  }, {
    "id" : 30002153
  }, {
    "id" : 30002151
  }, {
    "id" : 30002088
  }, {
    "id" : 30002084
  }, {
    "id" : 10859
  }, {
    "id" : 30002046
  }, {
    "id" : 30001793
  }, {
    "id" : 30001764
  }, {
    "id" : 10815
  }, {
    "id" : 30001631
  }, {
    "id" : 30001617
  }, {
    "id" : 10758
  }, {
    "id" : 30001360
  }, {
    "id" : 30001214
  }, {
    "id" : 30001157
  }, {
    "id" : 30001086
  }, {
    "id" : 10704
  }, {
    "id" : 10696
  }, {
    "id" : 10692
  }, {
    "id" : 10101
  }, {
    "id" : 10086
  } ]
}