{
  "id" : 7440,
  "handle" : "zizo0003",
  "countHistoryTasks" : 50,
  "historyTasks" : [ {
    "id" : 30101930
  }, {
    "id" : 30100149
  }, {
    "id" : 30095825
  }, {
    "id" : 30095824
  }, {
    "id" : 30095823
  }, {
    "id" : 30095821
  }, {
    "id" : 30092166
  }, {
    "id" : 30094383
  }, {
    "id" : 30091712
  }, {
    "id" : 30092483
  }, {
    "id" : 17427
  }, {
    "id" : 17416
  }, {
    "id" : 17321
  }, {
    "id" : 17405
  }, {
    "id" : 17058
  }, {
    "id" : 17080
  }, {
    "id" : 17081
  }, {
    "id" : 17079
  }, {
    "id" : 16996
  }, {
    "id" : 16937
  }, {
    "id" : 16950
  }, {
    "id" : 30058127
  }, {
    "id" : 16833
  }, {
    "id" : 16703
  }, {
    "id" : 16510
  }, {
    "id" : 16525
  }, {
    "id" : 16472
  }, {
    "id" : 16445
  }, {
    "id" : 16369
  }, {
    "id" : 16359
  }, {
    "id" : 30047358
  }, {
    "id" : 30046149
  }, {
    "id" : 30045514
  }, {
    "id" : 16154
  }, {
    "id" : 16153
  }, {
    "id" : 15570
  }, {
    "id" : 15024
  }, {
    "id" : 14584
  }, {
    "id" : 14581
  }, {
    "id" : 14525
  }, {
    "id" : 14503
  }, {
    "id" : 14495
  }, {
    "id" : 14455
  }, {
    "id" : 30016034
  }, {
    "id" : 14412
  }, {
    "id" : 14355
  }, {
    "id" : 14354
  }, {
    "id" : 14351
  }, {
    "id" : 13964
  }, {
    "id" : 13934
  } ]
}