{
  "id" : 9289,
  "handle" : "mercury_m",
  "countHistoryTasks" : 16,
  "historyTasks" : [ {
    "id" : 13564
  }, {
    "id" : 30001607
  }, {
    "id" : 30000623
  }, {
    "id" : 30000596
  }, {
    "id" : 10685
  }, {
    "id" : 30000495
  }, {
    "id" : 30000396
  }, {
    "id" : 30000395
  }, {
    "id" : 10678
  }, {
    "id" : 30000187
  }, {
    "id" : 30000189
  }, {
    "id" : 30000150
  }, {
    "id" : 30000143
  }, {
    "id" : 30000099
  }, {
    "id" : 24331153
  }, {
    "id" : 24206645
  } ]
}