{
  "id" : 11519,
  "handle" : "davincicode",
  "countHistoryTasks" : 22,
  "historyTasks" : [ {
    "id" : 30007423
  }, {
    "id" : 30007422
  }, {
    "id" : 30007152
  }, {
    "id" : 30007142
  }, {
    "id" : 30007149
  }, {
    "id" : 30007135
  }, {
    "id" : 30007116
  }, {
    "id" : 30007061
  }, {
    "id" : 30006853
  }, {
    "id" : 30006657
  }, {
    "id" : 30006559
  }, {
    "id" : 30006571
  }, {
    "id" : 30006564
  }, {
    "id" : 30006544
  }, {
    "id" : 30006312
  }, {
    "id" : 30006293
  }, {
    "id" : 30006272
  }, {
    "id" : 30006242
  }, {
    "id" : 15312909
  }, {
    "id" : 15251281
  }, {
    "id" : 15251316
  }, {
    "id" : 14992011
  } ]
}