{
  "id" : 11628,
  "handle" : "masakt",
  "countHistoryTasks" : 23,
  "historyTasks" : [ {
    "id" : 17179
  }, {
    "id" : 17153
  }, {
    "id" : 17149
  }, {
    "id" : 17143
  }, {
    "id" : 17092
  }, {
    "id" : 17058
  }, {
    "id" : 17080
  }, {
    "id" : 17081
  }, {
    "id" : 17079
  }, {
    "id" : 17086
  }, {
    "id" : 17036
  }, {
    "id" : 17063
  }, {
    "id" : 16996
  }, {
    "id" : 17052
  }, {
    "id" : 17007
  }, {
    "id" : 17004
  }, {
    "id" : 16959
  }, {
    "id" : 16997
  }, {
    "id" : 16981
  }, {
    "id" : 16958
  }, {
    "id" : 16950
  }, {
    "id" : 16910
  }, {
    "id" : 16944
  } ]
}