{
  "id" : 12664,
  "handle" : "TonyJ",
  "countHistoryTasks" : 250,
  "historyTasks" : [ {
    "id" : 30108180
  }, {
    "id" : 30094385
  }, {
    "id" : 30092303
  }, {
    "id" : 30108798
  }, {
    "id" : 30108674
  }, {
    "id" : 30108675
  }, {
    "id" : 30108037
  }, {
    "id" : 30108036
  }, {
    "id" : 30108038
  }, {
    "id" : 30108035
  }, {
    "id" : 30108673
  }, {
    "id" : 30108532
  }, {
    "id" : 30108355
  }, {
    "id" : 30108372
  }, {
    "id" : 30108353
  }, {
    "id" : 30107642
  }, {
    "id" : 30107067
  }, {
    "id" : 30106341
  }, {
    "id" : 30106340
  }, {
    "id" : 30106339
  }, {
    "id" : 30106338
  }, {
    "id" : 30107737
  }, {
    "id" : 30103825
  }, {
    "id" : 30106195
  }, {
    "id" : 30106385
  }, {
    "id" : 30106100
  }, {
    "id" : 30106769
  }, {
    "id" : 30106383
  }, {
    "id" : 30106606
  }, {
    "id" : 30104182
  }, {
    "id" : 30104784
  }, {
    "id" : 30105849
  }, {
    "id" : 30105831
  }, {
    "id" : 30105244
  }, {
    "id" : 30105243
  }, {
    "id" : 30105242
  }, {
    "id" : 30105241
  }, {
    "id" : 30105830
  }, {
    "id" : 30105642
  }, {
    "id" : 30105409
  }, {
    "id" : 30105692
  }, {
    "id" : 30105045
  }, {
    "id" : 30105408
  }, {
    "id" : 30104739
  }, {
    "id" : 30105486
  }, {
    "id" : 30105167
  }, {
    "id" : 30105165
  }, {
    "id" : 30104320
  }, {
    "id" : 30104319
  }, {
    "id" : 30104318
  }, {
    "id" : 30104317
  }, {
    "id" : 30104642
  }, {
    "id" : 30099956
  }, {
    "id" : 30104718
  }, {
    "id" : 30104249
  }, {
    "id" : 30104418
  }, {
    "id" : 30104644
  }, {
    "id" : 30104202
  }, {
    "id" : 30104203
  }, {
    "id" : 30104201
  }, {
    "id" : 30104626
  }, {
    "id" : 30104600
  }, {
    "id" : 30104159
  }, {
    "id" : 30104162
  }, {
    "id" : 30104420
  }, {
    "id" : 30104151
  }, {
    "id" : 30104150
  }, {
    "id" : 30104144
  }, {
    "id" : 30104146
  }, {
    "id" : 30104143
  }, {
    "id" : 30104135
  }, {
    "id" : 30104136
  }, {
    "id" : 30104134
  }, {
    "id" : 30104524
  }, {
    "id" : 30104417
  }, {
    "id" : 30103958
  }, {
    "id" : 30103745
  }, {
    "id" : 30103744
  }, {
    "id" : 30103980
  }, {
    "id" : 30103760
  }, {
    "id" : 30103753
  }, {
    "id" : 30099184
  }, {
    "id" : 30103782
  }, {
    "id" : 30103892
  }, {
    "id" : 30103823
  }, {
    "id" : 30103914
  }, {
    "id" : 30103885
  }, {
    "id" : 30103927
  }, {
    "id" : 30103781
  }, {
    "id" : 30103191
  }, {
    "id" : 30103664
  }, {
    "id" : 30103551
  }, {
    "id" : 30103155
  }, {
    "id" : 30103143
  }, {
    "id" : 30103195
  }, {
    "id" : 30103394
  }, {
    "id" : 30096611
  }, {
    "id" : 30092785
  }, {
    "id" : 30094205
  }, {
    "id" : 30103266
  }, {
    "id" : 30103145
  }, {
    "id" : 30102819
  }, {
    "id" : 30102897
  }, {
    "id" : 30102127
  }, {
    "id" : 30102818
  }, {
    "id" : 30101976
  }, {
    "id" : 30101930
  }, {
    "id" : 30102678
  }, {
    "id" : 30101891
  }, {
    "id" : 30101700
  }, {
    "id" : 30101338
  }, {
    "id" : 30101631
  }, {
    "id" : 30101361
  }, {
    "id" : 30099707
  }, {
    "id" : 30100621
  }, {
    "id" : 30101178
  }, {
    "id" : 30101183
  }, {
    "id" : 30099951
  }, {
    "id" : 30101337
  }, {
    "id" : 30100514
  }, {
    "id" : 30101084
  }, {
    "id" : 30100513
  }, {
    "id" : 30100626
  }, {
    "id" : 30100515
  }, {
    "id" : 30099749
  }, {
    "id" : 30099750
  }, {
    "id" : 30100163
  }, {
    "id" : 30099785
  }, {
    "id" : 30099795
  }, {
    "id" : 30099875
  }, {
    "id" : 30099945
  }, {
    "id" : 30096444
  }, {
    "id" : 30098948
  }, {
    "id" : 30095825
  }, {
    "id" : 30095824
  }, {
    "id" : 30095823
  }, {
    "id" : 30095821
  }, {
    "id" : 30099714
  }, {
    "id" : 30099715
  }, {
    "id" : 30099713
  }, {
    "id" : 30099775
  }, {
    "id" : 30099771
  }, {
    "id" : 30099298
  }, {
    "id" : 30098626
  }, {
    "id" : 30099138
  }, {
    "id" : 30098526
  }, {
    "id" : 30098863
  }, {
    "id" : 30098507
  }, {
    "id" : 30098902
  }, {
    "id" : 30098047
  }, {
    "id" : 30098900
  }, {
    "id" : 30098625
  }, {
    "id" : 30092166
  }, {
    "id" : 30098168
  }, {
    "id" : 30098248
  }, {
    "id" : 30098395
  }, {
    "id" : 30098394
  }, {
    "id" : 30097582
  }, {
    "id" : 30096593
  }, {
    "id" : 30096518
  }, {
    "id" : 30096592
  }, {
    "id" : 30095822
  }, {
    "id" : 30096586
  }, {
    "id" : 30094364
  }, {
    "id" : 30087501
  }, {
    "id" : 30095683
  }, {
    "id" : 30095774
  }, {
    "id" : 30095732
  }, {
    "id" : 30096412
  }, {
    "id" : 30096336
  }, {
    "id" : 30095381
  }, {
    "id" : 30095425
  }, {
    "id" : 30095640
  }, {
    "id" : 30095657
  }, {
    "id" : 30095471
  }, {
    "id" : 30095545
  }, {
    "id" : 30095555
  }, {
    "id" : 30095423
  }, {
    "id" : 30095018
  }, {
    "id" : 30095138
  }, {
    "id" : 30094741
  }, {
    "id" : 30094980
  }, {
    "id" : 30095269
  }, {
    "id" : 30094846
  }, {
    "id" : 30094843
  }, {
    "id" : 30094891
  }, {
    "id" : 30094131
  }, {
    "id" : 30094480
  }, {
    "id" : 30094128
  }, {
    "id" : 30094231
  }, {
    "id" : 30088355
  }, {
    "id" : 30092991
  }, {
    "id" : 30093468
  }, {
    "id" : 30091712
  }, {
    "id" : 30093917
  }, {
    "id" : 30093568
  }, {
    "id" : 30093414
  }, {
    "id" : 30091562
  }, {
    "id" : 30093329
  }, {
    "id" : 30093873
  }, {
    "id" : 30093841
  }, {
    "id" : 30093217
  }, {
    "id" : 30093043
  }, {
    "id" : 30093580
  }, {
    "id" : 30092990
  }, {
    "id" : 30093279
  }, {
    "id" : 30092640
  }, {
    "id" : 30092657
  }, {
    "id" : 30092483
  }, {
    "id" : 30093315
  }, {
    "id" : 30093527
  }, {
    "id" : 30093216
  }, {
    "id" : 30093565
  }, {
    "id" : 30093178
  }, {
    "id" : 30092988
  }, {
    "id" : 30093093
  }, {
    "id" : 30092481
  }, {
    "id" : 30093155
  }, {
    "id" : 30092313
  }, {
    "id" : 30092645
  }, {
    "id" : 30092190
  }, {
    "id" : 30092207
  }, {
    "id" : 30092649
  }, {
    "id" : 30092312
  }, {
    "id" : 30091807
  }, {
    "id" : 30092349
  }, {
    "id" : 30092222
  }, {
    "id" : 30091975
  }, {
    "id" : 30092274
  }, {
    "id" : 30092160
  }, {
    "id" : 30091826
  }, {
    "id" : 30091997
  }, {
    "id" : 30091708
  }, {
    "id" : 30092033
  }, {
    "id" : 30092302
  }, {
    "id" : 30091806
  }, {
    "id" : 30091939
  }, {
    "id" : 30091687
  }, {
    "id" : 30091597
  }, {
    "id" : 30091595
  }, {
    "id" : 30091147
  }, {
    "id" : 30091067
  }, {
    "id" : 30091667
  }, {
    "id" : 30091194
  }, {
    "id" : 30090922
  }, {
    "id" : 30090819
  }, {
    "id" : 30090608
  }, {
    "id" : 30090895
  }, {
    "id" : 30090894
  }, {
    "id" : 30090949
  } ]
}