{
  "id" : 17386,
  "handle" : "longaway",
  "countHistoryTasks" : 23,
  "historyTasks" : [ {
    "id" : 30002204
  }, {
    "id" : 30002173
  }, {
    "id" : 30002152
  }, {
    "id" : 30002088
  }, {
    "id" : 30002071
  }, {
    "id" : 30002033
  }, {
    "id" : 30001999
  }, {
    "id" : 30001877
  }, {
    "id" : 30001887
  }, {
    "id" : 30001873
  }, {
    "id" : 30001838
  }, {
    "id" : 30001793
  }, {
    "id" : 30001742
  }, {
    "id" : 30001536
  }, {
    "id" : 30001701
  }, {
    "id" : 30001646
  }, {
    "id" : 30001509
  }, {
    "id" : 30001460
  }, {
    "id" : 30001409
  }, {
    "id" : 30001349
  }, {
    "id" : 30000946
  }, {
    "id" : 30000810
  }, {
    "id" : 30000750
  } ]
}