{
  "id" : 19613,
  "handle" : "c4wrd",
  "countHistoryTasks" : 24,
  "historyTasks" : [ {
    "id" : 30098350
  }, {
    "id" : 30064886
  }, {
    "id" : 30064865
  }, {
    "id" : 30062112
  }, {
    "id" : 30061922
  }, {
    "id" : 30061899
  }, {
    "id" : 30061833
  }, {
    "id" : 30060609
  }, {
    "id" : 30060581
  }, {
    "id" : 30058068
  }, {
    "id" : 16892
  }, {
    "id" : 30055923
  }, {
    "id" : 30056063
  }, {
    "id" : 30055870
  }, {
    "id" : 30055503
  }, {
    "id" : 30055679
  }, {
    "id" : 30055101
  }, {
    "id" : 30055022
  }, {
    "id" : 30054726
  }, {
    "id" : 30053433
  }, {
    "id" : 30053396
  }, {
    "id" : 30053599
  }, {
    "id" : 30053392
  }, {
    "id" : 30053391
  } ]
}