{
  "id" : 21049,
  "handle" : "Jahred",
  "countHistoryTasks" : 28,
  "historyTasks" : [ {
    "id" : 30095825
  }, {
    "id" : 30097979
  }, {
    "id" : 30095544
  }, {
    "id" : 30097811
  }, {
    "id" : 30097705
  }, {
    "id" : 30095780
  }, {
    "id" : 30092872
  }, {
    "id" : 30093231
  }, {
    "id" : 30091598
  }, {
    "id" : 30089301
  }, {
    "id" : 30091690
  }, {
    "id" : 30091600
  }, {
    "id" : 30090438
  }, {
    "id" : 30090712
  }, {
    "id" : 30090680
  }, {
    "id" : 30090457
  }, {
    "id" : 30090691
  }, {
    "id" : 30090374
  }, {
    "id" : 30090144
  }, {
    "id" : 30088848
  }, {
    "id" : 30088557
  }, {
    "id" : 30088354
  }, {
    "id" : 30083257
  }, {
    "id" : 30079486
  }, {
    "id" : 30081256
  }, {
    "id" : 30079791
  }, {
    "id" : 30076905
  }, {
    "id" : 30065884
  } ]
}