{
  "id" : 26376,
  "handle" : "ningling60",
  "countHistoryTasks" : 15,
  "historyTasks" : [ {
    "id" : 30092616
  }, {
    "id" : 30091056
  }, {
    "id" : 30091055
  }, {
    "id" : 30091076
  }, {
    "id" : 30090607
  }, {
    "id" : 30074181
  }, {
    "id" : 30073458
  }, {
    "id" : 30073415
  }, {
    "id" : 30072710
  }, {
    "id" : 30072650
  }, {
    "id" : 30062877
  }, {
    "id" : 30062427
  }, {
    "id" : 30062511
  }, {
    "id" : 30061100
  }, {
    "id" : 30061526
  } ]
}