{
  "id" : 28672,
  "handle" : "aseeniksn",
  "countHistoryTasks" : 21,
  "historyTasks" : [ {
    "id" : 30054554
  }, {
    "id" : 30054569
  }, {
    "id" : 30054518
  }, {
    "id" : 30054413
  }, {
    "id" : 30054235
  }, {
    "id" : 30054316
  }, {
    "id" : 30054289
  }, {
    "id" : 30054274
  }, {
    "id" : 30054273
  }, {
    "id" : 30054266
  }, {
    "id" : 30054179
  }, {
    "id" : 30053897
  }, {
    "id" : 30054203
  }, {
    "id" : 30054048
  }, {
    "id" : 30053071
  }, {
    "id" : 30054002
  }, {
    "id" : 30053994
  }, {
    "id" : 30053943
  }, {
    "id" : 30053885
  }, {
    "id" : 30053881
  }, {
    "id" : 30053786
  } ]
}