{
  "id" : 31914,
  "handle" : "ZeroTau",
  "countHistoryTasks" : 16,
  "historyTasks" : [ {
    "id" : 30006851
  }, {
    "id" : 30006836
  }, {
    "id" : 30006850
  }, {
    "id" : 30006822
  }, {
    "id" : 30006820
  }, {
    "id" : 30006823
  }, {
    "id" : 30006794
  }, {
    "id" : 30006699
  }, {
    "id" : 30006745
  }, {
    "id" : 30006692
  }, {
    "id" : 30006695
  }, {
    "id" : 30006690
  }, {
    "id" : 30006675
  }, {
    "id" : 30006657
  }, {
    "id" : 30006583
  }, {
    "id" : 30006564
  } ]
}