{
  "id" : 50571,
  "handle" : "theakhilis",
  "countHistoryTasks" : 96,
  "historyTasks" : [ {
    "id" : 30047631
  }, {
    "id" : 30042671
  }, {
    "id" : 30042628
  }, {
    "id" : 30042738
  }, {
    "id" : 30042661
  }, {
    "id" : 30042708
  }, {
    "id" : 30042526
  }, {
    "id" : 30042560
  }, {
    "id" : 30042618
  }, {
    "id" : 30042465
  }, {
    "id" : 30042332
  }, {
    "id" : 30042341
  }, {
    "id" : 30042312
  }, {
    "id" : 30042349
  }, {
    "id" : 30041831
  }, {
    "id" : 30042122
  }, {
    "id" : 30041614
  }, {
    "id" : 30042063
  }, {
    "id" : 30042106
  }, {
    "id" : 30042047
  }, {
    "id" : 30042041
  }, {
    "id" : 30041926
  }, {
    "id" : 30041937
  }, {
    "id" : 30041870
  }, {
    "id" : 30041803
  }, {
    "id" : 30041726
  }, {
    "id" : 30041564
  }, {
    "id" : 30041563
  }, {
    "id" : 30041562
  }, {
    "id" : 30041686
  }, {
    "id" : 30041661
  }, {
    "id" : 30041528
  }, {
    "id" : 30041501
  }, {
    "id" : 30041483
  }, {
    "id" : 30041104
  }, {
    "id" : 30041250
  }, {
    "id" : 30041248
  }, {
    "id" : 30040951
  }, {
    "id" : 30041101
  }, {
    "id" : 30040995
  }, {
    "id" : 30040954
  }, {
    "id" : 30040947
  }, {
    "id" : 30040874
  }, {
    "id" : 30040488
  }, {
    "id" : 30040834
  }, {
    "id" : 30039205
  }, {
    "id" : 30039171
  }, {
    "id" : 30039286
  }, {
    "id" : 30039193
  }, {
    "id" : 30039176
  }, {
    "id" : 30039175
  }, {
    "id" : 30039251
  }, {
    "id" : 30039290
  }, {
    "id" : 30039211
  }, {
    "id" : 30039289
  }, {
    "id" : 30039288
  }, {
    "id" : 30039236
  }, {
    "id" : 30039247
  }, {
    "id" : 30039266
  }, {
    "id" : 30039273
  }, {
    "id" : 30040728
  }, {
    "id" : 30039275
  }, {
    "id" : 30039281
  }, {
    "id" : 30039264
  }, {
    "id" : 30039225
  }, {
    "id" : 30036125
  }, {
    "id" : 30039242
  }, {
    "id" : 30039227
  }, {
    "id" : 30039223
  }, {
    "id" : 30039219
  }, {
    "id" : 30039220
  }, {
    "id" : 30039174
  }, {
    "id" : 30040725
  }, {
    "id" : 30040722
  }, {
    "id" : 30040745
  }, {
    "id" : 30040738
  }, {
    "id" : 30040736
  }, {
    "id" : 30040737
  }, {
    "id" : 30040733
  }, {
    "id" : 30038548
  }, {
    "id" : 30038551
  }, {
    "id" : 30037782
  }, {
    "id" : 30037804
  }, {
    "id" : 30038486
  }, {
    "id" : 30037796
  }, {
    "id" : 30038529
  }, {
    "id" : 30038539
  }, {
    "id" : 30038533
  }, {
    "id" : 30038534
  }, {
    "id" : 30038530
  }, {
    "id" : 30038495
  }, {
    "id" : 30038492
  }, {
    "id" : 30038120
  }, {
    "id" : 30038520
  }, {
    "id" : 30038488
  }, {
    "id" : 30037590
  } ]
}