{
  "id" : 83837,
  "handle" : "deepu8",
  "countHistoryTasks" : 26,
  "historyTasks" : [ {
    "id" : 30040081
  }, {
    "id" : 30040258
  }, {
    "id" : 30040251
  }, {
    "id" : 30037051
  }, {
    "id" : 30038156
  }, {
    "id" : 30037115
  }, {
    "id" : 30036960
  }, {
    "id" : 30038076
  }, {
    "id" : 30037102
  }, {
    "id" : 30038050
  }, {
    "id" : 30038055
  }, {
    "id" : 30038046
  }, {
    "id" : 30038047
  }, {
    "id" : 30037950
  }, {
    "id" : 30038240
  }, {
    "id" : 30037300
  }, {
    "id" : 30038309
  }, {
    "id" : 30037245
  }, {
    "id" : 30038242
  }, {
    "id" : 30040193
  }, {
    "id" : 30038098
  }, {
    "id" : 30038147
  }, {
    "id" : 30040199
  }, {
    "id" : 30038057
  }, {
    "id" : 30038113
  }, {
    "id" : 30037915
  } ]
}